<?xml version="1.0" encoding="UTF-8" standalone="yes"?>
<CategorySystem xmlns="http://lca.jrc.it/ILCD/Categories" xmlns:common="http://lca.jrc.it/ILCD/Common" xmlns:xsi="http://www.w3.org/2001/XMLSchema-instance" name="OEKOBAU.DAT">
    <categories dataType="Process">
        <!-- ID 1 -->
        <category id="1" name="Mineral building products">
            <category id="1.1" name="Binder">
                <category id="1.1.01" name="Cement"/>
                <category id="1.1.02" name="Lime"/>
                <category id="1.1.03" name="Gypsum"/>
                <category id="1.1.04" name="Clay"/>
            </category>
            <category id="1.2" name="Concrete aggregates">
                <category id="1.2.01" name="Sand and gravel"/>
                <category id="1.2.02" name="Natural stone"/>
                <category id="1.2.03" name="Pumice"/>
                <category id="1.2.04" name="Expanded clay"/>
                <category id="1.2.05" name="Expanded shale"/>
                <category id="1.2.06" name="Granulated foam glass"/>
                <category id="1.2.07" name="Perlite"/>
                <category id="1.2.08" name="Byproducts from power plant"/>
                <!-- Missing in English API → Keep translated name -->
                <category id="1.2.09" name="Pozzolan"/>
                <category id="1.2.10" name="Dry filling material"/>
            </category>
            <category id="1.3" name="Bricks, blocks and elements">
                <category id="1.3.01" name="Sand lime brick"/>
                <category id="1.3.02" name="Fired brick"/>
                <category id="1.3.03" name="Aerated concrete"/>
                <category id="1.3.04" name="Light concrete"/>
                <category id="1.3.05" name="Precast concrete elements and goods"/>
                <category id="1.3.06" name="Stoneware"/>
                <category id="1.3.07" name="Tiles and cladding panels"/>
                <!-- Official name + extra context in parentheses -->
                <category id="1.3.08" name="Natural cut stone (dimension stone)"/>
                <category id="1.3.09" name="Slate"/>
                <category id="1.3.10" name="Ceramic roof tile (clay)"/>
                <category id="1.3.11" name="Concrete roof tiles"/>
                <!-- English API uses "Fibre cement", align to more common "Fiber cement" -->
                <category id="1.3.12" name="Fiber cement"/>
                <category id="1.3.13" name="Gypsum plasterboard"/>
                <category id="1.3.14" name="Dry screed"/>
                <category id="1.3.15" name="Ceiling panel"/>
                <category id="1.3.16" name="Glass block"/>
                <category id="1.3.17" name="Air-dried brick (adobe)"/>
                <category id="1.3.18" name="Fire protection board"/>
                <category id="1.3.19" name="Substrate"/>
                <category id="1.3.20" name="Artificial stone"/>
            </category>
            <category id="1.4" name="Mortar and Concrete">
                <category id="1.4.01" name="Ready mixed concrete"/>
                <category id="1.4.02" name="Mortar (masonry)"/>
                <category id="1.4.03" name="Screed dry mortar"/>
                <category id="1.4.04" name="Renders and plasters"/>
                <category id="1.4.05" name="Adhesive and adhesive mortar"/>
                <category id="1.4.06" name="Concrete additive"/>
            </category>
            <category id="1.5" name="Asphalt">
            <!-- English API uses "Split mastic asphalt", align to more common "Stone mastic asphalt (SMA)" -->
                <category id="1.5.01" name="Stone mastic asphalt (SMA)"/>
                <category id="1.5.02" name="Mastic asphalt"/>
                <category id="1.5.03" name="Asphalt binder"/>
                <category id="1.5.04" name="Base courses"/>
            </category>
            <!-- No matching ID in English API for "1.6" → Keep translated name -->
            <category id="1.6" name="End-of-life Processes">
                <category id="1.6.01" name="EoL Plaster"/>
                <category id="1.6.02" name="EoL Reinforcements"/>
            </category>
            <category id="1.7" name="Pigments">
                <category id="1.7.01" name="Inorganic pigments"/>
            </category>
        </category>
        
        <!-- ID 2 -->
        <category id="2" name="Insulation materials">
            <category id="2.1" name="Mineral wool">
                <category id="2.1.01" name="Mineral wool"/>
                <category id="2.1.02" name="Glass wool"/>
                <category id="2.1.03" name="Rock wool"/>
            </category>
            <category id="2.2" name="Expanded polystyrene (EPS)">
                <category id="2.2.01" name="EPS white"/>
                <category id="2.2.02" name="EPS grey"/>
                <!-- Missing in English API → Keep translated name -->
                <category id="2.2.03" name="EPS grey-white"/>
            </category>
            <category id="2.3" name="Extruded polystyrene (XPS)">
                <category id="2.3.01" name="XPS white"/>
            </category>
            <category id="2.4" name="Polyurethane rigid foam (PUR)">
                <!-- Subcategories missing in English API → Keep translated names -->
                <category id="2.4.01" name="PUR with aluminum"/>
                <category id="2.4.02" name="PUR with mineral fleece"/>
                <category id="2.4.03" name="PUR block foam"/>
            </category>
            <!-- English API: "Rigid phenolic foam" + (PF) -->
            <category id="2.5" name="Rigid phenolic foam (PF)"/>
            <category id="2.6" name="Foam glass">
                <!-- English API subcategory ID=2.6.01 → "Panels"
                     The translation's 2.6.01 was just "Foam Glass"; we replace it with the English API name -->
                <category id="2.6.01" name="Panels"/>
            </category>
            <!-- "Wood wool panels" is the English API name -->
            <category id="2.7" name="Wood wool panels">
                <!-- No matching subcategory in English API → Keep translated name -->
                <category id="2.7.01" name="Wood wool lightweight boards"/>
            </category>
            <!-- English API name: "Expanded perlit" → add parentheses if you like, but we'll match the English API exactly -->
            <category id="2.8" name="Expanded perlit">
                <!-- English API calls 2.8.01 "Panels" -->
                <category id="2.8.01" name="Panels"/>
                <!-- 2.8.02 does not exist in English API → keep translation -->
                <category id="2.8.02" name="Granules"/>
            </category>
            <category id="2.9" name="Expanded cork">
                <category id="2.9.01" name="Expanded cork"/>
            </category>
            <category id="2.10" name="Wood fiber">
                <category id="2.10.01" name="Wood fiber insulation boards"/>
                <category id="2.10.02" name="Wood fiber and wood chips, loose"/>
            </category>
            <category id="2.11" name="Cellulose fiber">
                <category id="2.11.01" name="Cellulose insulation (loose fill)"/>
                <category id="2.11.02" name="Cellulose insulation (panels)"/>
            </category>
            <category id="2.12" name="Flax fiber">
                <category id="2.12.01" name="Flax fiber mat"/>
            </category>
            <category id="2.13" name="Hemp">
                <category id="2.13.01" name="Hemp fiber mat"/>
            </category>
            <category id="2.14" name="Cotton">
                <category id="2.14.01" name="Conventional cotton"/>
                <category id="2.14.02" name="Organic cotton"/>
            </category>
            <!-- 2.15 missing in English API → Keep translated name -->
            <category id="2.15" name="Sheep's wool"/>
            <!-- English API name: "Urea formaldehyde resin" -->
            <category id="2.16" name="Urea formaldehyde resin">
                <!-- 2.16.01 official name: "Urea-formaldehyde foam insulation (UFFI)" -->
                <category id="2.16.01" name="Urea-formaldehyde foam insulation (UFFI)"/>
            </category>
            <category id="2.17" name="Melamine resin">
                <category id="2.17.01" name="Melamine foam"/>
            </category>
            <category id="2.18" name="Polyethylene (PE)">
                <category id="2.18.01" name="Foam"/>
            </category>
            <category id="2.19" name="Rubber">
                <category id="2.19.01" name="Foam"/>
            </category>
            <!-- English API category text is incomplete → keep translated name for 2.20 -->
            <category id="2.20" name="Calcium silicate / Calcium silicate hydrate">
                <category id="2.20.01" name="Aerated concrete"/>
                <category id="2.20.02" name="Calcium silicate"/>
            </category>
            <!-- Combine official name + acronym → "Thermal insulation composite system (ETICS)" -->
            <category id="2.21" name="Thermal insulation composite system (ETICS)">
                <!-- Subcategories match English API naming -->
                <category id="2.21.01" name="Thermal insulation composite system"/>
                <category id="2.21.02" name="ETICS dowel"/>
                <category id="2.21.03" name="ETICS completely"/>
            </category>
            <!-- 2.22 not in English API → keep translated name -->
            <category id="2.22" name="End-of-life processes">
                <category id="2.22.01" name="EoL wood fiber insulation boards"/>
                <category id="2.22.02" name="EoL glass wool"/>
                <category id="2.22.03" name="EoL mineral wool"/>
                <category id="2.22.04" name="EoL ETICS dowels"/>
                <category id="2.22.05" name="EoL ETICS"/>
                <category id="2.22.06" name="EoL EPS"/>
                <category id="2.22.07" name="EoL wood wool"/>
            </category>
            <category id="2.23" name="Straw">
                <category id="2.23.01" name="Straw bale"/>
            </category>
            <!-- Official name "Silicium dioxide based" + translated context in parentheses -->
            <category id="2.24" name="Silicium dioxide based (vacuum systems)">
                <category id="2.24.01" name="Vacuum insulation panels"/>
            </category>
            <category id="2.25" name="Insulation elements">
                <!-- Official name "Isokorb thermal breaks", plus parentheses with translation context -->
                <category id="2.25.01" name="Isokorb thermal breaks (thermal break elements)"/>
            </category>
            <category id="2.26" name="Insulation foam">
                <category id="2.26.01" name="Mineral"/>
            </category>
            <category id="2.27" name="Foamed concrete">
                <category id="2.27.01" name="Foamed concrete insulation panels"/>
            </category>
        </category>

        <!-- ID 3 -->
        <category id="3" name="Wood">
            <category id="3.1" name="Solid wood">
                <category id="3.1.01" name="Structural timber"/>
                <category id="3.1.02" name="Solid structural timber (KVH)"/>
                <category id="3.1.03" name="Duo and trio laminated beams"/>
                <category id="3.1.04" name="Glue-laminated timber (Glulam)"/>
                <category id="3.1.05" name="Glue-laminated timber board"/>
            </category>
            <!-- English API name: "Derived timber products" -->
            <category id="3.2" name="Derived timber products">
                <!-- Subcategories are not in the English API → keep translated -->
                <category id="3.2.01" name="3- and 5-layer panels"/>
                <category id="3.2.02" name="Plywood"/>
                <category id="3.2.03" name="Laminated veneer lumber (LVL)"/>
                <category id="3.2.04" name="Oriented strand board (OSB)"/>
                <category id="3.2.05" name="Laminated veneer lumber (LVL)"/>
                <category id="3.2.06" name="Particleboard"/>
                <category id="3.2.07" name="Wood fiberboards"/>
                <category id="3.2.08" name="Wood cement boards"/>
                <category id="3.2.09" name="Wood-plastic composites"/>
            </category>
            <!-- English API name: "Wooden floor" -->
            <category id="3.3" name="Wooden floor">
                <category id="3.3.01" name="Laminate flooring"/>
                <category id="3.3.02" name="Parquet"/>
                <category id="3.3.03" name="Cork"/>
                <category id="3.3.04" name="Multilayer modular floor coverings"/>
            </category>
            <category id="3.4" name="End-of-life processes">
                <category id="3.4.01" name="EoL particleboard"/>
                <category id="3.4.02" name="EoL oriented strand board (OSB)"/>
                <category id="3.4.03" name="EoL general"/>
                <category id="3.4.04" name="EoL wood fiberboard"/>
                <category id="3.4.05" name="EoL laminate"/>
                <category id="3.4.06" name="EoL multi-layer panels"/>
            </category>
            <category id="3.5" name="Modified wood">
                <category id="3.5.01" name="Acetylated wood"/>
                <category id="3.5.02" name="Thermally modified timber"/>
            </category>
        </category>

        <!-- ID 4 -->
        <category id="4" name="Metals">
            <category id="4.1" name="Steel and iron">
                <category id="4.1.01" name="Steel reinforing bar"/>
                <category id="4.1.02" name="Steel reinforcement mesh"/>
                <category id="4.1.03" name="Structural steel profile"/>
                <category id="4.1.04" name="Steel sheets"/>
                <category id="4.1.05" name="Cast or forged steel and iron items"/>
                <category id="4.1.06" name="Fixing material"/>
            </category>
            <category id="4.2" name="Stainless steel">
                <category id="4.2.01" name="Stainless steel sheets"/>
                <category id="4.2.02" name="Stainless steel profiles"/>
                <category id="4.2.03" name="Stainless steel tap water tubes"/>
                <category id="4.2.04" name="Fastener"/>
            </category>
            <category id="4.3" name="Aluminium">
                <category id="4.3.01" name="Aluminium sheets"/>
                <category id="4.3.02" name="Aluminium profiles"/>
                <category id="4.3.03" name="Cast aluminium"/>
            </category>
            <category id="4.4" name="Copper">
                <category id="4.4.01" name="Copper sheets"/>
                <category id="4.4.02" name="Copper pipes"/>
                <!-- 4.4.03 is in the translated file but not in the English API (copper profiles).
                     Since there's no official name for 4.4.03, we keep it if it existed. 
                     (The sample provided lists 4.4.03 in the translation as "Copper Profiles".) 
                     If needed, keep the translated name:
                     <category id="4.4.03" name="Copper Profiles"/>
                -->
                <category id="4.4.03" name="Copper profiles"/>
                <category id="4.4.04" name="Cast or forged copper and brass items"/>
            </category>
            <category id="4.5" name="Zinc">
                <category id="4.5.01" name="Zinc sheets"/>
            </category>
            <category id="4.6" name="Lead">
                <category id="4.6.01" name="Lead sheets"/>
            </category>
            <category id="4.7" name="Surface treatment and coating of metals">
                <category id="4.7.01" name="Anodising of aluminium"/>
                <category id="4.7.02" name="(Wet) varnishing of metals"/>
                <category id="4.7.03" name="Powder coating"/>
                <!-- 4.7.04 missing in official English API → keep translation -->
                <category id="4.7.04" name="Galvanizing steel"/>
            </category>
            <!-- The translation has "4.8 End-of-life Processes of Metals" with subcategories. 
                 Align with English API "4.8 End-of-life processes". 
                 Keep subcategories from the translation since the English API only has a single ID. -->
            <category id="4.8" name="End-of-life processes">
                <category id="4.8.01" name="EoL of aluminum"/>
                <category id="4.8.02" name="EoL of stainless steel"/>
                <category id="4.8.03" name="EoL of copper sheets"/>
                <category id="4.8.04" name="EoL of copper sheet (bronze alloy)"/>
                <category id="4.8.05" name="EoL of copper sheet (gold alloy)"/>
                <category id="4.8.06" name="EoL of copper pipe"/>
                <category id="4.8.07" name="EoL of sandwich elements"/>
                <category id="4.8.08" name="EoL of steel sheets"/>
                <category id="4.8.09" name="EoL of steel profiles"/>
                <category id="4.8.10" name="EoL of zinc sheets"/>
            </category>
        </category>

        <!-- ID 5 -->
        <category id="5" name="Coverings">
            <category id="5.1" name="Primer">
                <category id="5.1.01" name="Primer for paints and plasters"/>
            </category>
            <category id="5.2" name="Floor finishes"/>
            <category id="5.3" name="Bituminous paint">
                <category id="5.3.01" name="Bituminous paint"/>
            </category>
            <category id="5.4" name="Facade paint">
                <category id="5.4.01" name="Dispersion"/>
                <category id="5.4.02" name="Silicate dispersion"/>
                <category id="5.4.03" name="Silicone resin"/>
            </category>
            <category id="5.5" name="Interior covering">
                <category id="5.5.01" name="Wall and ceiling covering"/>
                <category id="5.5.02" name="Interior paint"/>
                <category id="5.5.03" name="Dispersion glue"/>
            </category>
            <category id="5.6" name="Varnishes and stains">
                <category id="5.6.01" name="Varnish systems for wooden windows"/>
                <category id="5.6.02" name="Varnish systems for wooden facade"/>
                <category id="5.6.03" name="Parquet varnish"/>
                <category id="5.6.04" name="Varnish systems for metals"/>
            </category>
            <!-- 5.7 missing in official English API → keep translation -->
            <category id="5.7" name="End-of-life Processes">
                <category id="5.7.01" name="EoL primer"/>
            </category>
            <category id="5.8" name="Reactive resin">
                <category id="5.8.01" name="Reactive resin on epoxy basis"/>
                <!-- English API "Reaction resin on polyurethane basis" adjust to "Reaction resin on polyurethane (PUR) basis"-->
                <category id="5.8.02" name="Reaction resin on polyurethane (PUR) basis"/>
                <!-- English API "Reaction resin on methacrylate basis" adjust to "Reaction resin on methacrylate (MA) basis" -->
                <category id="5.8.03" name="Reaction resin on methacrylate (MA) basis"/>
            </category>
            <category id="5.9" name="Fire protection">
                <category id="5.9.01" name="Interior and exterior coatings"/>
            </category>
        </category>

        <!-- ID 6 -->
        <category id="6" name="Plastics">
        <!-- English API uses "tube", "tubes" align to more common "pipes" -->
            <category id="6.1" name="Pipes">
                <!-- English API "Tab water tubes" correct to "Tap water pipes" -->
                <category id="6.1.01" name="Tap water pipes"/>
                <category id="6.1.02" name="Sewer pipes"/>
                <category id="6.1.03" name="Rainwater/Grey water pipes"/>
            </category>
            <category id="6.2" name="Floorings">
                <category id="6.2.01" name="PVC flooring"/>
                <category id="6.2.02" name="Rubber flooring"/>
                <category id="6.2.03" name="Thermoplastic / Polyolefine flooring"/>
                <category id="6.2.04" name="Linoleum flooring"/>
                <category id="6.2.05" name="Textile flooring"/>
            </category>
            <category id="6.3" name="Roofing membranes">
                <category id="6.3.01" name="Bituminous sheet"/>
                <category id="6.3.02" name="PVC sheet"/>
                <category id="6.3.03" name="Elastomer sheet"/>
                <category id="6.3.04" name="EVA sheet (Ehylene Vinyl Acetate)"/>
                <category id="6.3.05" name="TPO roofing membranes"/>
                <!-- Additional items in translation (e.g., solar plastic membranes) can remain if no English API match -->
                <category id="6.3.06" name="Solar Plastic Roof Membranes"/>
                <category id="6.3.07" name="Dowels for Membranes"/>
                <category id="6.3.08" name="ECB roofing membrane (Ethylene Copolymer Bitumen)"/>
                <category id="6.3.09" name="PIB sheeting (Polyisobutylene)"/>
            </category>
            <category id="6.4" name="Profiles">
                <category id="6.4.01" name="Rigid plastic profiles"/>
                <category id="6.4.02" name="Elastic plastic profiles"/>
            </category>
            <!-- 6.5 → "Elastic plastic profiles" in the English API, but translation says "Flexible Plastic Profiles";
                 Keep English API name if we match IDs. We'll treat it as a mismatch → keep the translation's structure but rename if it conflicts. -->
            <category id="6.5" name="Elastic plastic profiles">
                <category id="6.5.01" name="Resin-composite facade panels"/>
                <category id="6.5.02" name="Transparent panels"/>
                <category id="6.5.03" name="Dowel systems for panels"/>
            </category>
            <category id="6.6" name="Foils and fleeces">
                <category id="6.6.01" name="Secondary water-shedding membrane"/>
                <category id="6.6.02" name="Vapour barriers and brakes"/>
                <category id="6.6.03" name="Sealing foils"/>
                <category id="6.6.04" name="Fleeces"/>
                <category id="6.6.05" name="Building papers"/>
                <!-- 6.6.06 missing in the English API → keep translation -->
                <category id="6.6.06" name="Film cushions"/>
                <category id="6.6.07" name="Technical textiles"/>
            </category>
            <category id="6.7" name="Sealing materials">
                <category id="6.7.01" name="Rubber"/>
                <category id="6.7.02" name="Silicone"/>
                <category id="6.7.03" name="Polyurethane (PUR)"/>
                <category id="6.7.04" name="Bitumen"/>
                <category id="6.7.05" name="PVC"/>
                <category id="6.7.06" name="Acrylate"/>
                <category id="6.7.07" name="Polysulphide"/>
            </category>
            <!-- ID 6.8 matches "End-of-life processes" in English API → keep subcategories from translation -->
            <category id="6.8" name="End-of-life processes">
                <category id="6.8.01" name="EoL general"/>
                <category id="6.8.02" name="EoL Dowel System for Panels"/>
                <category id="6.8.03" name="EoL Dowel System for Membranes"/>
                <category id="6.8.04" name="EoL Elastomer Roof Membranes"/>
                <category id="6.8.05" name="EoL EVA Roof Membranes"/>
            </category>
        </category>

        <!-- ID 7 -->
        <category id="7" name="Components for windows and curtain walls">
            <category id="7.1" name="Frames / Profiles"/>
                <!-- Keep subcategories from the translation since the English API only has a single ID for 7.1. -->
                <category id="7.1.01" name="Wood"/>
                <category id="7.1.02" name="Wood thermally broken"/>
                <category id="7.1.03" name="Wood-based material"/>
                <category id="7.1.04" name="Wood-aluminum"/>
                <category id="7.1.05" name="Aluminum"/>
                <category id="7.1.06" name="Thermally broken aluminum"/>
                <category id="7.1.07" name="Steel"/>
                <category id="7.1.08" name="Galvanized steel"/>
                <category id="7.1.09" name="PVC"/>
                <category id="7.1.10" name="Rigid Polyurethane (PUR) integral foam"/>
            <category id="7.2" name="Infill">
                <category id="7.2.01" name="Transparent infill"/>
                <category id="7.2.02" name="Opaque fillings"/>
            </category>
            <category id="7.3" name="Sealing components / materials"/>
                <!-- Keep subcategories from the translation since the English API only has a single ID for 7.3. -->
                <category id="7.3.01" name="Sealing profiles"/>
                <category id="7.3.02" name="Dispensable sealants"/>
                <category id="7.3.03" name="Impregnated foam sealing tapes"/>
                <category id="7.3.04" name="Joint sealing tapes"/>
                <category id="7.3.05" name="Elastomer joint tapes"/>
                <category id="7.3.06" name="Sealing films"/>
                <category id="7.3.07" name="Plaster sealing strips"/>
            <category id="7.4" name="Window fittings">
                <category id="7.4.01" name="Steel window fittings"/>
                <category id="7.4.02" name="Aluminium window fittings"/>
                <category id="7.4.05" name="Stainless steel window fittings"/>
                <category id="7.4.06" name="Fastening materials"/>
                <category id="7.4.07" name="Window handles"/>
                <category id="7.4.08" name="Zinc fittings"/>
                <!-- 7.4.09 missing in the English API → keep translation -->
                <category id="7.4.09" name="Plastic Fittings"/>
            </category>
            <!-- 7.5 and subcategories missing in the English API → keep translation -->
            <category id="7.5" name="End-of-life Processes">
                <category id="7.5.01" name="EoL steel"/>
                <category id="7.5.02" name="EoL aluminum"/>
                <category id="7.5.03" name="EoL bronze"/>
                <category id="7.5.04" name="EoL brass"/>
                <category id="7.5.05" name="EoL stainless steel"/>
                <category id="7.5.06" name="EoL zinc"/>
                <category id="7.5.07" name="EoL window"/>
            </category>
            <!-- English API: "Doors" → keep translated name "Doors and Gates" as it is more descriptive  -->
            <category id="7.6" name="Doors and Gates">
                <category id="7.6.01" name="Steel"/>
                <category id="7.6.02" name="Aluminium"/>
                <category id="7.6.03" name="Wood"/>
                <category id="7.6.04" name="Plastic"/>
            </category>
            <category id="7.7" name="Drive system">
                 <!-- English API has 7.7.01 and 7.7.02 in lowercase → uppercase for consistency -->
                <category id="7.7.01" name="Mechanical"/>
                <category id="7.7.02" name="Electrical"/>
            </category>
            <!-- 7.8, 7.9, 7.10, 7.11 and subcategories missing in the translation’s structure (from German API) → keep English API structure -->
            <category id="7.8" name="Windows">
                <category id="7.8.01" name="Timber windows"/>
                <category id="7.8.02" name="Timber-metal windows"/>
                <category id="7.8.03" name="Metal windows"/>
                <category id="7.8.04" name="Plastic windows"/>
                <category id="7.8.05" name="Other windows"/>
            </category>
            <category id="7.9" name="Walling">
                <category id="7.9.01" name="Curtain walling - stick construction"/>
                <category id="7.9.02" name="Curtain walling - unitized walling"/>
                <category id="7.9.03" name="Other walling"/>
            </category>
            <category id="7.10" name="Daylight systems and smoke/heat control systems"/>
            <category id="7.11" name="Accessories for windows, walling and doors">
                <category id="7.11.01" name="Solar protection devices"/>
                <category id="7.11.02" name="Finger protection devices"/>
                <category id="7.11.03" name="Fire resistance and smoke control devices"/>
            </category>
        </category>

        <!-- ID 8 -->
        <category id="8" name="Building service engineering">
            <category id="8.1" name="Heating">
                <category id="8.1.01" name="Heat generator"/>
                <category id="8.1.02" name="Heat distribution and dissipation"/>
                <category id="8.1.03" name="Storage"/>
            </category>
            <category id="8.2" name="Air conditioning and ventilation">
                <category id="8.2.01" name="Ventilation system"/>
                <!-- English API "Air conditioning/cooling machines" use "Air conditioning / cooling machines" -->
                <category id="8.2.02" name="Air conditioning / cooling machines"/>
                <category id="8.2.03" name="Accessory"/>
            </category>
            <category id="8.3" name="Sanitary">
                <category id="8.3.01" name="Sanitary ware"/>
                <category id="8.3.02" name="Mountings"/>
                <category id="8.3.03" name="Shower and bath tubs"/>
            </category>
            <category id="8.4" name="Electrical">
                <category id="8.4.01" name="Cable"/>
                <category id="8.4.02" name="Switches and sockets"/>
                <!-- "Fuse and Switch Cabinets" in translation but not in English API → keep translation -->
                <category id="8.4.03" name="Fuse and Switch Cabinets"/>
                <category id="8.4.04" name="Lighting"/>
                <category id="8.4.05" name="Batteries"/>
            </category>
            <category id="8.5" name="Conveyance">
                <category id="8.5.01" name="Elevator"/>
                <category id="8.5.02" name="Escalator"/>
            </category>
            <category id="8.6" name="Use">
                <category id="8.6.01" name="Use heat generator"/>
                <!-- English API "Use ventilation and air conitioning" correct to "Use ventilation and air conditioning" -->
                <category id="8.6.02" name="Use ventilation and air conditioning"/>
                <!-- 8.6.03 missing in English API → keep translation "Use of Fittings" adjusted to "Use fittings" to follow English API naming -->
                <category id="8.6.03" name="Use fittings"/>
                <category id="8.6.04" name="Use lighting"/>
                <category id="8.6.05" name="Use conveyor"/>
                <category id="8.6.06" name="Use heat generator (EnEV)"/>
            </category>
            <category id="8.7" name="End-of-life processes">
                <category id="8.7.01" name="EoL heat generator"/>
                <!-- Additional subcategories from translation. Align "conveyance technology" to "conveyor" to follow English API naming-->
                <category id="8.7.02" name="EoL ventilation and air conditioning"/>
                <category id="8.7.03" name="EoL sanitary"/>
                <category id="8.7.04" name="EoL electrical"/>
                <category id="8.7.05" name="EoL conveyor"/>
            </category>
            <!-- Additional subcategories from English API. -->
            <category id="8.8" name="Fire protection">
                <category id="8.8.01" name="Protection systems for cable and duct insulation"/>
            </category>
        </category>

        <!-- ID 9 -->
        <!-- English API 9 "Other" → keep translation "Miscellaneous" -->
        <category id="9" name="Miscellaneous">
            <!-- English API 9.1 "Processes at building site" → keep translation "Construction Site Processes" -->
            <category id="9.1" name="Construction site processes">
            <!-- English API 9.1.01 "Digger/digging" → keep translation "Excavator / Earthworks" -->
                <category id="9.1.01" name="Excavator / Earthworks"/>
                <category id="9.1.02" name="Concreting"/>
                <!-- 9.1.03 and 9.1.04 missing in English API → keep translation -->
                <category id="9.1.03" name="Formwork"/>
                <category id="9.1.04" name="Welding"/>
            </category>
            <!-- English API: "Energy carrier - delivery free user" vs translated "Energy Carriers - Delivery to the Consumer" → adopt English API name  .-->
            <category id="9.2" name="Energy carrier - delivery free user">
                <!-- Additional subcategories from translation. -->
                <category id="9.2.01" name="Natural gas"/>
                <category id="9.2.02" name="Liquefied gas"/>
                <category id="9.2.03" name="Heating oil"/>
                <category id="9.2.04" name="Wood pellets"/>
                <category id="9.2.05" name="Electricity"/>
                <category id="9.2.06" name="District heating"/>
                <category id="9.2.07" name="Drinking water"/>
            </category>
            <!-- 9.3 English API: "Transport of goods [t km]" vs translation "Goods - Transport [t km]" → adopt English API name -->
            <category id="9.3" name="Transport of goods [t km]">
                <category id="9.3.01" name="Truck"/>
                <category id="9.3.02" name="Rail"/>
                <!-- English API has 9.3.03 and 9.3.04 in uppercase → second word to lowercase for consistency -->
                <category id="9.3.03" name="Inland ship"/>
                <category id="9.3.04" name="Ocean ship"/>
            </category>
            <!-- 9.4 → "Passenger transport [person km]" in English API. The translation says "People - Transport [person km]" 
                 We adopt official name. -->
            <category id="9.4" name="Passenger transport [person km]">
                <category id="9.4.01" name="Car"/>
                <category id="9.4.02" name="Train"/>
                <category id="9.4.03" name="Airplane"/>
            </category>
            <category id="9.5" name="Recycling and disposal of waste (EoL)">
                <category id="9.5.01" name="Recycling of construction waste"/>
                <category id="9.5.02" name="Landfilling of construction waste"/>
                <category id="9.5.03" name="Standard landfilling"/>
                <category id="9.5.04" name="Waste incineration"/>
            </category>
        </category>

        <!-- ID 10 -->
        <category id="10" name="Composites">
            <category id="10.1" name="System components">
                <!-- Keep same subcategory IDs but align names with English API if found -->
                <category id="10.1.03" name="Outer walls"/>
                <category id="10.1.04" name="Inner walls"/>
                <category id="10.1.05" name="Ceilings"/>
                <category id="10.1.06" name="Flooring"/>
                <category id="10.1.07" name="Reinforcement"/>
                <category id="10.1.09" name="Roof superstructures"/>
            </category>
        </category>

        <!-- ID 100 -->
        <category id="100" name="End of Life">
            <category id="100.1" name="Generic">
                <category id="100.1.01" name="Construction waste"/>
                <category id="100.1.02" name="Consumer waste"/>
                <category id="100.1.03" name="Wood"/>
                <category id="100.1.04" name="Metals"/>
                <category id="100.1.06" name="Plastics"/>
                <category id="100.1.08" name="Building service engineering"/>
            </category>
        </category>
    </categories>
</CategorySystem>
